[{"Semester":"WiSe 2020/21","Link":null,"Stadt":"Berlin","Einrichtung":"Freie Universität Berlin","Institut":"Institut für Klassische Archäologie","Studiengang/Modul":"Master Klassische Archäologie;\nModul: Interdisziplinäre\nPerspektiven der Klassischen\nArchäologie","Veranstaltungstitel":"Datenkompetenz und Geoinformationssysteme in Den Altertumswissenschaften","Veranstaltungstyp":"Seminar","Zielgruppe":"MA","Lehrende":"Polla, Silvia","Inhalte":"Archivierung,\nDatenkuratierung,Spatial\nAnalysis,Metadaten,\nVisualisierung,GIS,\nDatenbanken,\nDatenmanagement,\nDatenpräsentation,\nDigitale Datenauswertung,\nDigitale Dokumentation,Dig. Methoden & Theorien,\nDigitalisierung,Digital Humanities,\nDigitale Ressourcen","Notiz":null,"Nachname":null,"Vorname":null,"Position":null,"id":595}]
