{"Semester":"SoSe 2015","Link":"NA","Stadt":"Bamberg","Einrichtung":"Universit\u00e4t Bamberg","Institut":"Arch\u00e4ologie, Denkmalkunde und Kunstgeschichte","Studiengang/Modul":"Informatiosverarbeitung in der Geoarch\u00e4ologie","Veranstaltungstitel":"Grundlagen, Theorie und Methodik, Vertiefung in Informationsverarbeitung der Geoarch\u00e4ologie","Veranstaltungstyp":"Exportmodul","Zielgruppe":"NA","Lehrende":"NA","Inhalte":"NA","Notiz":"NA","Nachname":"NA","Vorname":"NA","Position":"NA","id":169}
