[{"Semester":"WiSe 2017/18","Link":"http://archaeology.altertum.uni-halle.de/3436_2595808/2595808_3058752/2987893_30...","Stadt":"Halle","Einrichtung":"Seminar für Klassische Archäologie","Institut":"Institut für Kunstgeschichte und Archäologien Europas","Studiengang/Modul":"Hilfmittel und Techniken des Studiengangs","Veranstaltungstitel":"Datenbank Management, GIS und 3D-Visualisierung","Veranstaltungstyp":"Übung","Zielgruppe":"BA","Lehrende":"Köster, Jan","Inhalte":"3D-Modellierung,GIS,Datenbanken,Bildbearbeitung,Digitale Dokumentation,EDV,Digitalisierung,3D","Notiz":null,"Nachname":"Tanriöver","Vorname":"Aylin","Position":"Lehrender","id":97}]
