{"Semester":"SoSe 2021","Link":"NA","Stadt":"M\u00fcnster","Einrichtung":"Westf\u00e4lische Wilhelms-Universit\u00e4t M\u00fcnster","Institut":"Historisches Seminar - Abteilung f\u00fcr Ur- und\nFr\u00fchgeschichtliche Arch\u00e4ologie","Studiengang/Modul":"MA Modul 2","Veranstaltungstitel":"Theorie und Anwendung statistischer Methoden zur Gr\u00e4berfeld- und Siedlungsanalyse","Veranstaltungstyp":"\u00dcbung","Zielgruppe":"BA, MA","Lehrende":"Siegmund, Frank","Inhalte":"Statistik,Datenbanken,Digitale Datenauswertung","Notiz":"NA","Nachname":"NA","Vorname":"NA","Position":"NA","id":692}
